x/__init__.py
x/ai/__init__.py
x/ai/gemini.py
x/ai/grok.py
x/ai/grok_openai.py
x/browser/__init__.py
x/browser/browser.py
x/browser/xpage.py
x/cli.py
x/githubx/__init__.py
x/githubx/github.py
x/githubx/github_user.py
x/os/__init__.py
x/os/cpu.py
x/os/env.py
x/os/file.py
x/os/folder.py
x/os/gpu.py
x/os/path.py
x/os/shell.py
x/server/Server.py
x/server/__init__.py
x/telebot.py
x/utils/__init__.py
x/utils/json.py
x/zmt/__init__.py
x/zmt/小红书类.py
xx0-0.1.1.dist-info/METADATA
xx0-0.1.1.dist-info/WHEEL
xx0-0.1.1.dist-info/entry_points.txt
xx0-0.1.1.dist-info/RECORD
