Metadata-Version: 2.1
Name: xx0
Version: 0.1.1
Summary: 包的简短描述
Requires-Python: >=3.10
Classifier: Programming Language :: Python :: 3
Classifier: Programming Language :: Python :: 3.10
Classifier: Programming Language :: Python :: 3.11
Classifier: Programming Language :: Python :: 3.12
Classifier: Programming Language :: Python :: 3.13
Requires-Dist: openai (>=1.54.4,<2.0.0)
Requires-Dist: playwright (>=1.48.0,<2.0.0)
Requires-Dist: pygithub (>=2.5.0,<3.0.0)
Requires-Dist: python-dotenv (>=1.0.1,<2.0.0)
Requires-Dist: typer (==0.9.0)
